yaml_to_backend/__init__.py
yaml_to_backend/app.py
yaml_to_backend/cli.py
yaml_to_backend/config.py
yaml_to_backend/api/__init__.py
yaml_to_backend/api/auth_routes.py
yaml_to_backend/api/crud_generator.py
yaml_to_backend/core/__init__.py
yaml_to_backend/core/entity_parser.py
yaml_to_backend/core/model_generator.py
yaml_to_backend/db/__init__.py
yaml_to_backend/db/connection.py
yaml_to_backend/db/generated_models.py
yaml_to_backend/db/models.py
yaml_to_backend/security/__init__.py
yaml_to_backend/security/auth.py
yaml_to_backend-0.1.15.dist-info/licenses/LICENSE
yaml_to_backend-0.1.15.dist-info/METADATA
yaml_to_backend-0.1.15.dist-info/WHEEL
yaml_to_backend-0.1.15.dist-info/entry_points.txt
yaml_to_backend-0.1.15.dist-info/top_level.txt
yaml_to_backend-0.1.15.dist-info/RECORD
