Metadata-Version: 2.4
Name: yaml-to-backend
Version: 0.1.15
Summary: Generador de Backends a partir de YAML
Author-email: IPAS Team <info@ipas.com>
Maintainer-email: IPAS Team <info@ipas.com>
License: MIT
Project-URL: Homepage, https://github.com/cxmjg/yaml-to-backend
Project-URL: Documentation, https://github.com/cxmjg/yaml-to-backend#readme
Project-URL: Repository, https://github.com/cxmjg/yaml-to-backend
Project-URL: Bug Tracker, https://github.com/cxmjg/yaml-to-backend/issues
Keywords: yaml,backend,generator,fastapi,sqlalchemy,crud
Classifier: Development Status :: 4 - Beta
Classifier: Intended Audience :: Developers
Classifier: License :: OSI Approved :: MIT License
Classifier: Operating System :: OS Independent
Classifier: Programming Language :: Python :: 3
Classifier: Programming Language :: Python :: 3.10
Classifier: Programming Language :: Python :: 3.11
Classifier: Programming Language :: Python :: 3.12
Classifier: Programming Language :: Python :: 3.13
Classifier: Topic :: Software Development :: Code Generators
Classifier: Topic :: Internet :: WWW/HTTP :: Dynamic Content
Classifier: Topic :: Database
Requires-Python: >=3.10
License-File: LICENSE
Requires-Dist: fastapi>=0.104.0
Requires-Dist: uvicorn[standard]>=0.24.0
Requires-Dist: sqlalchemy>=2.0.0
Requires-Dist: sqlmodel>=0.0.8
Requires-Dist: pydantic>=2.0.0
Requires-Dist: pyyaml>=6.0
Requires-Dist: bcrypt>=4.0.0
Requires-Dist: python-jose[cryptography]>=3.3.0
Requires-Dist: python-multipart>=0.0.6
Requires-Dist: asyncmy>=0.2.8
Requires-Dist: python-dotenv>=1.0.0
Requires-Dist: inflection>=0.5.0
Requires-Dist: passlib[bcrypt]>=1.7.0
Provides-Extra: dev
Requires-Dist: pytest>=7.0.0; extra == "dev"
Requires-Dist: pytest-asyncio>=0.21.0; extra == "dev"
Requires-Dist: httpx>=0.24.0; extra == "dev"
Requires-Dist: black>=23.0.0; extra == "dev"
Requires-Dist: flake8>=6.0.0; extra == "dev"
Dynamic: license-file
